{
  "name": "Time Stream",
  "number": "85808813",
  "is_illegal": false,
  "text": "Target 1 \"Fossil\" Fusion Monster you control; Tribute it, and if you do, Special Summon 1 \"Fossil\" Fusion Monster from your Extra Deck, whose original Level is 2 higher than that monster's. (This is treated as a Fusion Summon with \"Fossil Fusion\".) During your Main Phase, except the turn this card was sent to the GY: You can banish this card and 1 \"Fossil\" Fusion Monster from your GY, then target 1 \"Fossil\" Fusion Monster in your GY; Special Summon it.",
  "type": "Spell",
  "is_monster": false,
  "is_spell": true,
  "is_trap": false,
  "property": "Normal"
}